config_wrangler/__init__.py
config_wrangler/config_data_loaders/__init__.py
config_wrangler/config_data_loaders/base_config_data_loader.py
config_wrangler/config_data_loaders/env_config_data_loader.py
config_wrangler/config_data_loaders/file_config_data_loader.py
config_wrangler/config_data_loaders/ini_config_data_loader.py
config_wrangler/config_data_loaders/toml_config_data_loader.py
config_wrangler/config_exception.py
config_wrangler/config_from_ini.py
config_wrangler/config_from_ini_env.py
config_wrangler/config_from_loaders.py
config_wrangler/config_from_toml_env.py
config_wrangler/config_root.py
config_wrangler/config_templates/__init__.py
config_wrangler/config_templates/aws/__init__.py
config_wrangler/config_templates/aws/aws_session.py
config_wrangler/config_templates/aws/dynamodb.py
config_wrangler/config_templates/aws/lambda.py
config_wrangler/config_templates/aws/s3_bucket.py
config_wrangler/config_templates/aws/secrets_manager.py
config_wrangler/config_templates/aws/ssm.py
config_wrangler/config_templates/config_hierarchy.py
config_wrangler/config_templates/credentials.py
config_wrangler/config_templates/keepass_config.py
config_wrangler/config_templates/logging_config.py
config_wrangler/config_templates/password_defaults.py
config_wrangler/config_templates/password_source.py
config_wrangler/config_templates/sqlalchemy_database.py
config_wrangler/config_types/__init__.py
config_wrangler/config_types/delimited_field.py
config_wrangler/config_types/dynamically_referenced.py
config_wrangler/config_types/enum.py
config_wrangler/config_types/path_types.py
config_wrangler/config_wrangler_config.py
config_wrangler/utils.py
config_wrangler/validate_config_hierarchy.py
config_wrangler-1.3.1.dist-info/LICENSE
config_wrangler-1.3.1.dist-info/LICENSE.txt
config_wrangler-1.3.1.dist-info/METADATA
config_wrangler-1.3.1.dist-info/WHEEL
config_wrangler-1.3.1.dist-info/RECORD
