Metadata-Version: 2.3
Name: config_wrangler
Version: 1.3.1
Summary: pydantic based configuration wrangler. Handles reading multiple ini or toml files with inheritance rules and variable expansions.
License: MIT
Author: Derek Wood
Requires-Python: >=3.10,<4.0.0
Classifier: License :: OSI Approved :: MIT License
Classifier: Programming Language :: Python :: 3
Classifier: Programming Language :: Python :: 3.10
Classifier: Programming Language :: Python :: 3.11
Classifier: Programming Language :: Python :: 3.12
Classifier: Programming Language :: Python :: 3.13
Provides-Extra: aws
Provides-Extra: aws-request-auth
Provides-Extra: keyring
Provides-Extra: pykeepass
Provides-Extra: redshift
Provides-Extra: s3
Provides-Extra: sqlalchemy
Provides-Extra: toml
Requires-Dist: SQLAlchemy (>=1.4) ; extra == "sqlalchemy"
Requires-Dist: StrEnum (>=0.4.7)
Requires-Dist: auto-all (>=1.4.1)
Requires-Dist: boto3 (>=1.38) ; extra == "redshift" or extra == "s3" or extra == "aws"
Requires-Dist: cachetools (>=5.3.1) ; extra == "s3" or extra == "aws"
Requires-Dist: keyring (>=23.9.3) ; extra == "keyring"
Requires-Dist: pydantic (>=2.0)
Requires-Dist: pydicti (>=1.1.6)
Requires-Dist: pykeepass (>=4.0.0) ; extra == "pykeepass"
Requires-Dist: requests-aws4auth (>=1.2.3) ; extra == "aws-request-auth"
Requires-Dist: toml (>=0.10.2) ; extra == "toml"
Requires-Dist: typing-extensions (>=4.7.1)
Project-URL: Documentation, https://bietl.dev/config_wrangler/
Project-URL: Repository, https://github.com/arcann/config_wrangler
